AUTHORS.rst
CHANGES.rst
CONTRIBUTORS.txt
LICENSE
MANIFEST.in
README.rst
requirements.txt
setup.cfg
setup.py
test-requirements.txt
lshash/__init__.py
lshash/lshash.py
lshash/storage.py
lshash3.egg-info/PKG-INFO
lshash3.egg-info/SOURCES.txt
lshash3.egg-info/dependency_links.txt
lshash3.egg-info/not-zip-safe
lshash3.egg-info/requires.txt
lshash3.egg-info/top_level.txt
tests/__init__.py
tests/conftest.py
tests/test_spheres.py