Metadata-Version: 1.1
Name: lshash3
Version: 0.0.8
Summary: A fast Python implementation of locality sensitive hashing with persistance (Redis) support.
Home-page: http://...
Author: Kay Zhu
Author-email: me@kayzhu.com
License: MIT
Platform: UNKNOWN
Classifier: Development Status :: 4 - Beta
Classifier: Programming Language :: Python
Classifier: Programming Language :: Python :: 2
Classifier: Programming Language :: Python :: 3
Classifier: Intended Audience :: Developers
Classifier: License :: OSI Approved :: MIT License
Classifier: Operating System :: OS Independent
Classifier: Topic :: Software Development :: Libraries
